some_aiohttp_service/__init__.py
some_aiohttp_service/base_service.py
some_aiohttp_service/exceptions.py
some_aiohttp_service/job.py
some_aiohttp_service-0.1.7.dist-info/LICENSE
some_aiohttp_service-0.1.7.dist-info/METADATA
some_aiohttp_service-0.1.7.dist-info/WHEEL
some_aiohttp_service-0.1.7.dist-info/RECORD
