Metadata-Version: 2.1
Name: some-aiohttp-service
Version: 0.1.7
Summary: Runner framework for aiohttp
Home-page: https://github.com/tommmlij/some-aiohttp-service
License: MIT
Author: tommmlij
Author-email: tommmlij@gmail.com
Requires-Python: >=3.9,<3.13
Classifier: License :: OSI Approved :: MIT License
Classifier: Programming Language :: Python :: 3
Classifier: Programming Language :: Python :: 3.9
Classifier: Programming Language :: Python :: 3.10
Classifier: Programming Language :: Python :: 3.11
Classifier: Programming Language :: Python :: 3.12
Requires-Dist: aiohttp (>=3.11,<4.0)
Project-URL: GitHub: issues, https://github.com/tommmlij/some-aiohttp-service/issues
Project-URL: GitHub: repo, https://github.com/tommmlij/some-aiohttp-service
